mloggers/__init__.py
mloggers/console_logger.py
mloggers/file_logger.py
mloggers/logger.py
mloggers/multi_logger.py
mloggers/wandb_logger.py
mloggers-2.2.1.dist-info/METADATA
mloggers-2.2.1.dist-info/WHEEL
mloggers-2.2.1.dist-info/licenses/LICENSE
mloggers-2.2.1.dist-info/RECORD
