Metadata-Version: 2.1
Name: mloggers
Version: 2.2.1
Summary: A collection of loggers for machine learning experiments.
Project-URL: Homepage, https://github.com/serhez/mloggers
Project-URL: Issues, https://github.com/serhez/mloggers/issues
Author-email: Sergio Hernandez Gutierrez <contact.sergiohernandez@gmail.com>
License-File: LICENSE
Classifier: License :: OSI Approved :: MIT License
Classifier: Operating System :: OS Independent
Classifier: Programming Language :: Python :: 3
Requires-Python: >=3.10
Requires-Dist: numpy
Requires-Dist: omegaconf
Requires-Dist: termcolor
Requires-Dist: wandb
